pyehub/BatchRunExcel.py
pyehub/__init__.py
pyehub/batchruns.py
pyehub/batchruns_Test.py
pyehub/ci.py
pyehub/datacollect.py
pyehub/epsilon_constraint.py
pyehub/excel_to_request_format.py
pyehub/logger.py
pyehub/multi_run_period.py
pyehub/multiple_hubs.py
pyehub/network_to_request_format.py
pyehub/outputter.py
pyehub/run.py
pyehub/time_resolved_carbon_factors.py
pyehub/viz.py
pyehub/data_formats/__init__.py
pyehub/data_formats/response_format.py
pyehub/data_formats/request_format/__init__.py
pyehub/data_formats/request_format/capacity.py
pyehub/data_formats/request_format/converter.py
pyehub/data_formats/request_format/network.py
pyehub/data_formats/request_format/request_format.py
pyehub/data_formats/request_format/storage.py
pyehub/data_formats/request_format/stream.py
pyehub/data_formats/request_format/time_series.py
pyehub/energy_hub/__init__.py
pyehub/energy_hub/ehub_model.py
pyehub/energy_hub/input_data.py
pyehub/energy_hub/param_var.py
pyehub/energy_hub/utils.py
pyehub/pylp/__init__.py
pyehub/pylp/constraint.py
pyehub/pylp/expression.py
pyehub/pylp/problem.py
pyehub/pylp/tutorial.py
pyehub/pylp/variable.py
pyehub-1.5.0.dist-info/METADATA
pyehub-1.5.0.dist-info/WHEEL
pyehub-1.5.0.dist-info/top_level.txt
pyehub-1.5.0.dist-info/RECORD
