Metadata-Version: 2.1
Name: pyehub
Version: 1.5.0
Summary: A library used to solve an energy hub model in Python.
Home-page: https://gitlab.com/energyincities/python-ehub
Author-email: revins@uvic.ca
Classifier: Programming Language :: Python :: 3
Classifier: License :: OSI Approved :: GNU General Public License (GPL)
Classifier: Operating System :: OS Independent
Requires-Dist: pulp
Requires-Dist: contexttimer
Requires-Dist: pandas
Requires-Dist: numpy
Requires-Dist: PyYAML
Requires-Dist: xlrd
Requires-Dist: jsonschema
Requires-Dist: pylint
Requires-Dist: openpyxl
Requires-Dist: defusedxml
